openlis/__init__.py
openlis/data/__init__.py
openlis/data/data_set.py
openlis/database/__init__.py
openlis/database/index_structures.py
openlis/database/index_structures_gapped.py
openlis/database/index_structures_packed-backup.py
openlis/database/index_structures_packed.py
openlis/database/utils.py
openlis/model/__init__.py
openlis/model/recursive_model_index_simple.py
openlis/model/recursive_model_index_simple_any_layers_nonorm.py
openlis/model/recursive_model_index_simple_two_layers_only.py
openlis/notebooks/__init__.py
openlis-1.0.dev7.dist-info/DESCRIPTION.rst
openlis-1.0.dev7.dist-info/METADATA
openlis-1.0.dev7.dist-info/RECORD
openlis-1.0.dev7.dist-info/WHEEL
openlis-1.0.dev7.dist-info/metadata.json
openlis-1.0.dev7.dist-info/top_level.txt
