Metadata-Version: 2.0
Name: openlis
Version: 1.0.dev7
Summary: Implementation of Learned Index Structures
Home-page: http://github.com/amorten/openlis
Author: Andrew Morten
Author-email: andio.m@gmail.com
License: MIT
Platform: UNKNOWN
Requires-Python: >=3
Requires-Dist: numpy
Requires-Dist: tensorflow
